deep_refactor/__init__.py
deep_refactor/main.py
deeprefactorCLI-0.1.1.dist-info/METADATA
deeprefactorCLI-0.1.1.dist-info/WHEEL
deeprefactorCLI-0.1.1.dist-info/entry_points.txt
deeprefactorCLI-0.1.1.dist-info/top_level.txt
deeprefactorCLI-0.1.1.dist-info/RECORD
